setup.py
python_thumbs.egg-info/PKG-INFO
python_thumbs.egg-info/SOURCES.txt
python_thumbs.egg-info/dependency_links.txt
python_thumbs.egg-info/not-zip-safe
python_thumbs.egg-info/pbr.json
python_thumbs.egg-info/top_level.txt
scripts/thumbs
thumbs/__init__.py
thumbs/exceptions.py
thumbs/filetypes.py
thumbs/thumbnails.py
thumbs/types/__init__.py
thumbs/types/base.py
thumbs/types/docs.py
thumbs/types/image.py
thumbs/types/pdf.py
thumbs/types/sourcecode.py
thumbs/types/video.py