Metadata-Version: 1.1
Name: python-thumbs
Version: 0.1.1
Summary: Package description
